odoo/addons/base_sequence_default/README.rst
odoo/addons/base_sequence_default/__init__.py
odoo/addons/base_sequence_default/__manifest__.py
odoo/addons/base_sequence_default/demo/ir_sequence_demo.xml
odoo/addons/base_sequence_default/i18n/base_sequence_default.pot
odoo/addons/base_sequence_default/models/__init__.py
odoo/addons/base_sequence_default/models/base.py
odoo/addons/base_sequence_default/readme/CONFIGURE.rst
odoo/addons/base_sequence_default/readme/CONTRIBUTORS.rst
odoo/addons/base_sequence_default/readme/DESCRIPTION.rst
odoo/addons/base_sequence_default/readme/USAGE.rst
odoo/addons/base_sequence_default/static/description/icon.png
odoo/addons/base_sequence_default/static/description/index.html
odoo/addons/base_sequence_default/tests/__init__.py
odoo/addons/base_sequence_default/tests/test_project_project.py
odoo14_addon_base_sequence_default-14.0.1.0.0.dist-info/METADATA
odoo14_addon_base_sequence_default-14.0.1.0.0.dist-info/WHEEL
odoo14_addon_base_sequence_default-14.0.1.0.0.dist-info/top_level.txt
odoo14_addon_base_sequence_default-14.0.1.0.0.dist-info/RECORD
